phys/__init__.py
phys/constants.py
phys/elements.py
phys/pdg_2017_elements.dat
phys/units.py
phys-0.1.0.dist-info/METADATA
phys-0.1.0.dist-info/RECORD
phys-0.1.0.dist-info/WHEEL
phys-0.1.0.dist-info/top_level.txt
